setup.py
bin/elephunk
elephunk/__init__.py
elephunk/application.py
elephunk/database.py
elephunk/ui_methods.py
elephunk/ui_modules.py
elephunk.egg-info/PKG-INFO
elephunk.egg-info/SOURCES.txt
elephunk.egg-info/dependency_links.txt
elephunk.egg-info/requires.txt
elephunk.egg-info/top_level.txt
elephunk/handlers/__init__.py
elephunk/handlers/activity_handler.py
elephunk/handlers/base_handler.py
elephunk/handlers/bloat_database_handler.py
elephunk/handlers/bloat_server_handler.py
elephunk/handlers/buffer_cache_database_handler.py
elephunk/handlers/buffer_cache_server_handler.py
elephunk/handlers/indexes_database_handler.py
elephunk/handlers/indexes_server_handler.py
elephunk/handlers/indexes_table_handler.py
elephunk/handlers/root_handler.py
elephunk/handlers/select_server_handler.py
elephunk/records/__init__.py
elephunk/records/activity.py
elephunk/records/database.py
elephunk/records/index_io_stats.py
elephunk/records/sequence_io_stats.py
elephunk/records/table_io_stats.py