Metadata-Version: 1.0
Name: elephunk
Version: 0.0.2
Summary: PostgreSQL Investigation Console
Home-page: https://github.com/pitluga/elephunk
Author: Tony Pitluga
Author-email: tony.pitluga@gmail.com
License: MIT
Platform: UNKNOWN
